SURF/__init__.py
SURF/test.py
SURF/test2.py
SURF/models/WTM.py
SURF/models/__init__.py
SURF/models/wae.py
cellsurf/__init__.py
cellsurf/test.py
cellsurf/test2.py
cellsurf/models/WTM.py
cellsurf/models/__init__.py
cellsurf/models/wae.py
genesurf/__init__.py
genesurf/test.py
genesurf/test2.py
genesurf/models/WTM.py
genesurf/models/__init__.py
genesurf/models/wae.py
genesurf-0.1.dist-info/LICENSE
genesurf-0.1.dist-info/METADATA
genesurf-0.1.dist-info/WHEEL
genesurf-0.1.dist-info/entry_points.txt
genesurf-0.1.dist-info/top_level.txt
genesurf-0.1.dist-info/RECORD
